LICENSE
README.md
setup.py
down_detector_scraper/__init__.py
down_detector_scraper.egg-info/PKG-INFO
down_detector_scraper.egg-info/SOURCES.txt
down_detector_scraper.egg-info/dependency_links.txt
down_detector_scraper.egg-info/requires.txt
down_detector_scraper.egg-info/top_level.txt