Metadata-Version: 2.1
Name: down-detector-scraper
Version: 1.0.0
Summary: A python library to scrape down detector
Home-page: UNKNOWN
Author: DataKund
Author-email: datakund@gmail.com
License: Apache License 2.0
Keywords: downdetector,python,bot_studio,automation,search,scraper,scrape
Platform: UNKNOWN
License-File: LICENSE
